helixdam/__init__.py
helixdam-0.1.4.dist-info/LICENSE
helixdam-0.1.4.dist-info/METADATA
helixdam-0.1.4.dist-info/WHEEL
helixdam-0.1.4.dist-info/top_level.txt
helixdam-0.1.4.dist-info/RECORD
