Metadata-Version: 2.1
Name: helixdam
Version: 0.1.4
Summary: A Python wrapper for Perforce Helix DAM REST API
Author-email: Jase Lindgren <jclindgren@gmail.com>
Project-URL: Homepage, https://github.com/jase-perf/helixdam
Classifier: Programming Language :: Python :: 3
Classifier: License :: OSI Approved :: MIT License
Classifier: Operating System :: OS Independent
Requires-Python: >=3.8
License-File: LICENSE
Requires-Dist: requests
